pyoorb.cpython-39-aarch64-linux-gnu.so
pyoorb-1.3.0.dist-info/top_level.txt
pyoorb-1.3.0.dist-info/RECORD
pyoorb-1.3.0.dist-info/WHEEL
pyoorb-1.3.0.dist-info/COPYING
pyoorb-1.3.0.dist-info/METADATA
pyoorb.libs/libgfortran-8634ef04.so.3.0.0
pyoorb.libs/libblas-d36778f5.so.3.4.2
pyoorb.libs/liblapack-29219182.so.3.4.2
pyoorb.libs/libgfortran-daac5196.so.5.0.0
