Metadata-Version: 2.1
Name: pyoorb
Version: 1.3.0
Summary: An open-source orbit-computation package for Solar System objects. 
Home-page: https://github.com/oorb/oorb
Download-URL: https://pypi.python.org/pypi/pyoorb
Author: Mikael Granvik et al.
Maintainer: oorb developers
Maintainer-email: oorb@googlegroups.com
License: GPL3
Project-URL: Bug Tracker, https://github.com/oorb/oorb/issues
Project-URL: Source Code, https://github.com/oorb/oorb
License-File: COPYING
